spotifySync/__init__.py
spotifySync-2021.6.16.dist-info/METADATA
spotifySync-2021.6.16.dist-info/WHEEL
spotifySync-2021.6.16.dist-info/entry_points.txt
spotifySync-2021.6.16.dist-info/top_level.txt
spotifySync-2021.6.16.dist-info/RECORD
