Metadata-Version: 2.1
Name: spotifySync
Version: 2021.6.16
Summary: Sync Spotify Account.
Home-page: UNKNOWN
Author: YaronH
Author-email: yaronhuang@foxmail.com
License: Apache2
Platform: any
Requires-Dist: aigpy
Requires-Dist: spotipy
